hunabku_dri_udea/__init__.py
hunabku_dri_udea/_version.py
hunabku_dri_udea/endpoints/dri_udea.py
Hunabku_dri_udea-0.0.3.dist-info/METADATA
Hunabku_dri_udea-0.0.3.dist-info/WHEEL
Hunabku_dri_udea-0.0.3.dist-info/top_level.txt
Hunabku_dri_udea-0.0.3.dist-info/RECORD
