Metadata-Version: 2.1
Name: Hunabku-dri-udea
Version: 0.0.3
Summary: Hunabku plugin from the International Affairs Office of the university of Antioquia
Home-page: https://github.com/colav/Hunabku_plugins
Author: Colav
Author-email: colav@udea.edu.co
License: BSD
Requires-Dist: flask (>=1.1.2)
Requires-Dist: requests (>=2.22.0)
Requires-Dist: hunabku
